planteye_vision/__init__.py
planteye_vision/common/__init__.py
planteye_vision/common/camera_status.py
planteye_vision/common/timestamp.py
planteye_vision/configuration/__init__.py
planteye_vision/configuration/configuration.py
planteye_vision/configuration/inlet_configuration.py
planteye_vision/configuration/planteye_configuration.py
planteye_vision/configuration/processor_configuration.py
planteye_vision/configuration/shell_configuration.py
planteye_vision/configuration/upload_config_dummy_request.py
planteye_vision/data_chunks/__init__.py
planteye_vision/data_chunks/data_chunk.py
planteye_vision/data_chunks/data_chunk_data.py
planteye_vision/data_chunks/data_chunk_status.py
planteye_vision/data_chunks/metadata_chunk.py
planteye_vision/inlet/__init__.py
planteye_vision/inlet/baumer_camera_inlet.py
planteye_vision/inlet/camera_inlet.py
planteye_vision/inlet/generic_camera_inlet.py
planteye_vision/inlet/generic_camera_video_inlet.py
planteye_vision/inlet/inlet.py
planteye_vision/inlet/opcua_data_inlet.py
planteye_vision/inlet/restapi_inlet.py
planteye_vision/inlet/static_data_inlet.py
planteye_vision/pipeline_execution/__init__.py
planteye_vision/pipeline_execution/pipeline_executor.py
planteye_vision/processors/__init__.py
planteye_vision/processors/chunks_to_dict_processor.py
planteye_vision/processors/data_processor.py
planteye_vision/processors/encode_image_chunks_to_base_64_processor.py
planteye_vision/processors/image_color_conversion_processor.py
planteye_vision/processors/image_crop_processor.py
planteye_vision/processors/image_resize_processor.py
planteye_vision/processors/input_processor.py
planteye_vision/processors/pt_model_inference_processor.py
planteye_vision/processors/save_on_disc_processor.py
planteye_vision/processors/tf_model_inference_processor.py
planteye_vision/shell/__init__.py
planteye_vision/shell/periodical_local_shell.py
planteye_vision/shell/rest_api_shell.py
planteye_vision/shell/shell.py
planteye_vision-1.1.4.dist-info/LICENSE
planteye_vision-1.1.4.dist-info/METADATA
planteye_vision-1.1.4.dist-info/WHEEL
planteye_vision-1.1.4.dist-info/top_level.txt
planteye_vision-1.1.4.dist-info/RECORD
