Metadata-Version: 2.1
Name: planteye-vision
Version: 1.1.4
Summary: PlantEye-Vision
Home-page: UNKNOWN
Author: Valentin Khaydarov
Author-email: valentin.khaydarov@gmail.com
License: MIT
Platform: UNKNOWN
License-File: LICENSE
